odoo/addons/website_sale_hide_empty_category/README.rst
odoo/addons/website_sale_hide_empty_category/__init__.py
odoo/addons/website_sale_hide_empty_category/__manifest__.py
odoo/addons/website_sale_hide_empty_category/i18n/ca.po
odoo/addons/website_sale_hide_empty_category/i18n/es.po
odoo/addons/website_sale_hide_empty_category/i18n/it.po
odoo/addons/website_sale_hide_empty_category/i18n/nl.po
odoo/addons/website_sale_hide_empty_category/i18n/pt_BR.po
odoo/addons/website_sale_hide_empty_category/i18n/website_sale_hide_empty_category.pot
odoo/addons/website_sale_hide_empty_category/models/__init__.py
odoo/addons/website_sale_hide_empty_category/models/product_public_category.py
odoo/addons/website_sale_hide_empty_category/readme/CONFIGURE.md
odoo/addons/website_sale_hide_empty_category/readme/CONTRIBUTORS.md
odoo/addons/website_sale_hide_empty_category/readme/DESCRIPTION.md
odoo/addons/website_sale_hide_empty_category/readme/USAGE.md
odoo/addons/website_sale_hide_empty_category/static/description/icon.png
odoo/addons/website_sale_hide_empty_category/static/description/index.html
odoo/addons/website_sale_hide_empty_category/static/src/js/tour.esm.js
odoo/addons/website_sale_hide_empty_category/tests/__init__.py
odoo/addons/website_sale_hide_empty_category/tests/test_has_product_recursive.py
odoo/addons/website_sale_hide_empty_category/tests/test_ui.py
odoo/addons/website_sale_hide_empty_category/views/website_sale_templates.xml
odoo_addon_website_sale_hide_empty_category-18.0.1.0.0.5.dist-info/METADATA
odoo_addon_website_sale_hide_empty_category-18.0.1.0.0.5.dist-info/WHEEL
odoo_addon_website_sale_hide_empty_category-18.0.1.0.0.5.dist-info/top_level.txt
odoo_addon_website_sale_hide_empty_category-18.0.1.0.0.5.dist-info/RECORD
